setup.py
mobile_address/__init__.py
mobile_address/api.py
mobile_address.egg-info/PKG-INFO
mobile_address.egg-info/SOURCES.txt
mobile_address.egg-info/dependency_links.txt
mobile_address.egg-info/requires.txt
mobile_address.egg-info/top_level.txt