Metadata-Version: 1.1
Name: mobile-address
Version: 0.0.1
Summary: A simple app for searching mobile address.
Home-page: https://github.com/whatwewant/mobile-address
Author: Cole Smith
Author-email: tobewhatwewant@gmail.com
License: BSD License
Platform: UNKNOWN
Classifier: Intended Audience :: Developers
Classifier: License :: OSI Approved :: BSD License
Classifier: Operating System :: OS Independent
Classifier: Programming Language :: Python
Classifier: Programming Language :: Python :: 3
Classifier: Programming Language :: Python :: 3.4
Classifier: Programming Language :: Python :: 3.5
Classifier: Topic :: Internet :: WWW/HTTP
Classifier: Topic :: Internet :: WWW/HTTP :: Dynamic Content
